AUTHORS.md
HISTORY.md
LICENSE
MANIFEST.in
README.md
setup.cfg
setup.py
dbbackup_ui/__init__.py
dbbackup_ui/apps.py
dbbackup_ui/forms.py
dbbackup_ui/urls.py
dbbackup_ui/utils.py
dbbackup_ui/views.py
dbbackup_ui/templates/.DS_Store
dbbackup_ui/templates/dbbackup_ui/_backup_forms.html
dbbackup_ui/templates/dbbackup_ui/backup_view.html
dbbackup_ui/wagtail/__init__.py
dbbackup_ui/wagtail/apps.py
dbbackup_ui/wagtail/wagtail_hooks.py
dbbackup_ui/wagtail/templates/wagtail/backup_view.html
django_dbbackup_ui.egg-info/PKG-INFO
django_dbbackup_ui.egg-info/SOURCES.txt
django_dbbackup_ui.egg-info/dependency_links.txt
django_dbbackup_ui.egg-info/not-zip-safe
django_dbbackup_ui.egg-info/pbr.json
django_dbbackup_ui.egg-info/requires.txt
django_dbbackup_ui.egg-info/top_level.txt