Metadata-Version: 1.1
Name: django-dbbackup-ui
Version: 0.1.5
Summary: Backup database and media files via Django admin interface (includes Wagtail admin support)
Home-page: https://github.com/timonweb/django-dbbackup-ui
Author: Tim Kamanin
Author-email: tim@timonweb.com
License: BSD license
Keywords: django,database,media,backup,admin,wagtail,ui,download
Platform: UNKNOWN
Classifier: Development Status :: 3 - Alpha
Classifier: Environment :: Web Environment
Classifier: Framework :: Django
Classifier: Intended Audience :: Developers
Classifier: Intended Audience :: System Administrators
Classifier: License :: OSI Approved :: BSD License
Classifier: Natural Language :: English
Classifier: Programming Language :: Python :: 3
Classifier: Programming Language :: Python :: 3.3
Classifier: Programming Language :: Python :: 3.4
Classifier: Programming Language :: Python :: 3.5
Classifier: Programming Language :: Python :: 3.6
Classifier: Topic :: Database
Classifier: Topic :: System :: Archiving
Classifier: Topic :: System :: Archiving :: Backup
Classifier: Topic :: System :: Archiving :: Compression
